Workbook

Sheet DELIVERY 2024 COST
A1: DATE | B1: ITEM CODE | C1: ITEM DESCRIPTION | D1: UOM | E1: DELIVERY | F1: D/N NO AND R/V NO | G1: UNIT PRICE
A2: 45294 | B2: 401101620001 | C2: Fibre Board (MDF) 4x8x 3mm - MD03 /HAVING MORTHAN 2 ITEM NO | D2: SHT | E2: 500 | F2: BBMC DN-24200011 | G2: =IFERROR(VLOOKUP(B2,'MAIN 0'!$A$2:$C$6861,3,0),0) -> 10.5
A3: 45297 | B3: 631101840005 | C3: Eps Sheet 244x122x10cm D-16-18K.g | D3: SHT | E3: 20 | F3: NPPF INV 2024-00023 | G3: =IFERROR(VLOOKUP(B3,'MAIN 0'!$A$2:$C$6861,3,0),0) -> 65.17
A4: 45297 | B4: 631101840006 | C4: Eps Sheet 244x122x3cm D-16-18K.g | D4: SHT | E4: 30 | F4: NPPF INV 2024-00023 | G4: =IFERROR(VLOOKUP(B4,'MAIN 0'!$A$2:$C$6861,3,0),0) -> 21.88
A5: 45299 | B5: 401101840442 | C5: STEEL TUBE 16X16X1.5MM | D5: Pcs | E5: 170 | F5: QATAR STEEL DN-67560 | G5: =IFERROR(VLOOKUP(B5,'MAIN 0'!$A$2:$C$6861,3,0),0) -> 12.25
A6: 45299 | B6: 401101840496 | C6: Rec.Angle Tube 40x20x1.5mm | D6: PCS | E6: 20 | F6: QATAR STEEL DN-67560 | G6: =IFERROR(VLOOKUP(B6,'MAIN 0'!$A$2:$C$6861,3,0),0) -> 22
A7: 45299 | B7: 401101840493 | C7: STEEL TUBE 19X19X1.5MM | D7: PCS | E7: 120 | F7: QATAR STEEL DN-67560 | G7: =IFERROR(VLOOKUP(B7,'MAIN 0'!$A$2:$C$6861,3,0),0) -> 14.9
A8: 45299 | B8: 401101840397 | C8: STEEL TUBE 30X30X1.5MM | D8: Pcs | E8: 70 | F8: QATAR STEEL DN-67560 | G8: =IFERROR(VLOOKUP(B8,'MAIN 0'!$A$2:$C$6861,3,0),0) -> 22.5
A9: 45299 | B9: 401101840406 | C9: Round Bar 8mm | D9: Pcs | E9: 600 | F9: AL ITTEFAQ INV 24-00495 | G9: =IFERROR(VLOOKUP(B9,'MAIN 0'!$A$2:$C$6861,3,0),0) -> 7.5
A10: 45300 | B10: 521101840011 | C10: G.I Pipe 2"X1.5mm | D10: DRM | E10: 36 | F10: QATAR STEEL DN-67586 | G10: =IFERROR(VLOOKUP(B10,'MAIN 0'!$A$2:$C$6861,3,0),0) -> 45
A11: 45300 | B11: 631101840005 | C11: Eps Sheet 244x122x10cm D-16-18K.g | D11: SHT | E11: 12 | F11: NPPF DN-00139 | G11: =IFERROR(VLOOKUP(B11,'MAIN 0'!$A$2:$C$6861,3,0),0) -> 65.17
A12: 45299 | B12: 401101840500 | C12: Double Side Tape1" 25mmX50Mtr - Star Tape - Ind | D12: PCS | E12: 72 | F12: UNISTAR DN-51690 | G12: =IFERROR(VLOOKUP(B12,'MAIN 0'!$A$2:$C$6861,3,0),0) -> 35
A13: 45301 | B13: 110310390023 | C13: GARBAGE BAGS BLACK 80 X 110 | D13: BDL | E13: 20 | F13: ORIENT PLASTIC DN-208846 | G13: =IFERROR(VLOOKUP(B13,'MAIN 0'!$A$2:$C$6861,3,0),0) -> 110
... A1228: 45631 | B1228: 401101840401 | C1228: STEEL PIPE 3cmx1.5mm | D1228: Pcs | E1228: 3 | F1228: AL ITTEFAQ DN-24-18845 | G1228: =IFERROR(VLOOKUP(B1228,'MAIN 0'!$A$2:$C$6861,3,0),0) -> 32

Sheet OLD
M1: STEEL FABRICATION
A2: DATE | B2: ITEM DESCRIPTION | C2: ITEM CODE | D2: DATE | E2: ITEM DESCRIPTION | F2: UOM | G2: COST | H2: D/N NO | I2: CATEGORY | J2: TYPE | M2: DATE OF DELIVERY | N2: ITEM DESCRIPTION | O2: UNIT PRICE | P2: QTY | Q2: TOTAL PRICE
A3: 45638 | B3: Grinding Disk 4.5" | C3: 091101840002 | D3: 45638 | E3: Grinding Disk 4.5" | F3: PCS | G3: 3.5 | H3: AL ABDULLA TRDG DN-22834 | I3: STEEL FABRICATION CON | J3: STEEL FABRICATION | M3: =IFERROR(VLOOKUP(N3,$B$3:$G$508,3,0),0) -> 0 | O3: =IFERROR(VLOOKUP(N3,$B$3:$G$508,6,0),0) -> 0 | Q3: =PRODUCT(O3,P3) -> 0
A4: 45636 | B4: STEEL TUBE 30X30X1.5MM | C4: 401101840397 | D4: 45636 | E4: STEEL TUBE 30X30X1.5MM | F4: Pcs | G4: 22.5 | H4: QATAR STEEL DN NO- 74734 INV NO-120808 | I4: STEEL FABRICATION | J4: STEEL FABRICATION | M4: =IFERROR(VLOOKUP(N4,$B$3:$G$508,3,0),0) -> 0 | O4: =IFERROR(VLOOKUP(N4,$B$3:$G$508,6,0),0) -> 0 | Q4: =PRODUCT(O4,P4) -> 0
A5: 45634 | B5: Rec.Angle Tube 40x20x1.5mm | C5: 401101840496 | D5: 45634 | E5: Rec.Angle Tube 40x20x1.5mm | F5: PCS | G5: 22 | H5: QATAR STEEL DN-74680 | I5: STEEL FABRICATION | J5: STEEL FABRICATION | M5: =IFERROR(VLOOKUP(N5,$B$3:$G$508,3,0),0) -> 0 | O5: =IFERROR(VLOOKUP(N5,$B$3:$G$508,6,0),0) -> 0 | Q5: =PRODUCT(O5,P5) -> 0
A6: 45634 | B6: STEEL TUBE 40X40X1.5MM | C6: 401101840413 | D6: 45634 | E6: STEEL TUBE 40X40X1.5MM | F6: Pcs | G6: 29.5 | H6: QATAR STEEL DN-74680 | I6: STEEL FABRICATION | J6: STEEL FABRICATION | M6: =IFERROR(VLOOKUP(N6,$B$3:$G$508,3,0),0) -> 0 | O6: =IFERROR(VLOOKUP(N6,$B$3:$G$508,6,0),0) -> 0 | Q6: =PRODUCT(O6,P6) -> 0
A7: 45631 | B7: STEEL PIPE 3cmx1.5mm | C7: 401101840401 | D7: 45631 | E7: STEEL PIPE 3cmx1.5mm | F7: Pcs | G7: 32 | H7: AL ITTEFAQ DN-24-18845 | I7: STEEL FABRICATION | J7: STEEL FABRICATION | M7: =IFERROR(VLOOKUP(N7,$B$3:$G$508,3,0),0) -> 0 | O7: =IFERROR(VLOOKUP(N7,$B$3:$G$508,6,0),0) -> 0 | Q7: =PRODUCT(O7,P7) -> 0
A8: 45630 | B8: G.I Pipe 1"- ½ X3X6m | C8: 521101840018 | D8: 45630 | E8: G.I Pipe 1"- ½ X3X6m | F8: PCS | G8: 66.75 | H8: QATAR STEEL DN-24604 | I8: STEEL FABRICATION | J8: STEEL FABRICATION | M8: =IFERROR(VLOOKUP(N8,$B$3:$G$508,3,0),0) -> 0 | O8: =IFERROR(VLOOKUP(N8,$B$3:$G$508,6,0),0) -> 0 | Q8: =PRODUCT(O8,P8) -> 0
A9: 45630 | B9: STEEL TUBE 16X16X1.5MM | C9: 401101840442 | D9: 45630 | E9: STEEL TUBE 16X16X1.5MM | F9: Pcs | G9: 12.25 | H9: QATAR STEEL DN-24604 | I9: STEEL FABRICATION | J9: STEEL FABRICATION | M9: =IFERROR(VLOOKUP(N9,$B$3:$G$508,3,0),0) -> 0 | O9: =IFERROR(VLOOKUP(N9,$B$3:$G$508,6,0),0) -> 0 | Q9: =PRODUCT(O9,P9) -> 0
A10: 45623 | B10: Hummer Flap Disc G-80 4.5" | C10: 601101840002 | D10: 45623 | E10: Hummer Flap Disc G-80 4.5" | F10: PCS | G10: 2.5 | H10: AL ABDULLA TRDG DN-22802 | I10: STEEL FABRICATION CON | J10: STEEL FABRICATION | M10: =IFERROR(VLOOKUP(N10,$B$3:$G$508,3,0),0) -> 0 | O10: =IFERROR(VLOOKUP(N10,$B$3:$G$508,6,0),0) -> 0 | Q10: =PRODUCT(O10,P10) -> 0
A11: 45623 | B11: Round Bar 8mm | C11: 401101840406 | D11: 45623 | E11: Round Bar 8mm | F11: Pcs | G11: 7.5 | H11: QATAR STEEL INV NO-120290 -120291 | I11: STEEL FABRICATION | J11: STEEL FABRICATION | M11: =IFERROR(VLOOKUP(N11,$B$3:$G$508,3,0),0) -> 0 | O11: =IFERROR(VLOOKUP(N11,$B$3:$G$508,6,0),0) -> 0 | Q11: =PRODUCT(O11,P11) -> 0
A12: 45620 | B12: STEEL TUBE 25X25X1.5MM | C12: 401101840396 | D12: 45620 | E12: STEEL TUBE 25X25X1.5MM | F12: Pcs | G12: 20 | H12: QATAR STEEL DN-76442 | I12: STEEL FABRICATION | J12: STEEL FABRICATION | M12: =IFERROR(VLOOKUP(N12,$B$3:$G$508,3,0),0) -> 0 | O12: =IFERROR(VLOOKUP(N12,$B$3:$G$508,6,0),0) -> 0 | Q12: =PRODUCT(O12,P12) -> 0
A13: 45619 | B13: Welding Electrode E6013 | C13: 1166 | D13: 45619 | E13: Welding Electrode E6013 | F13: Pkt | G13: 14 | H13: AL ABDULLA TRDG DN-22140 | I13: STEEL FABRICATION CON | J13: STEEL FABRICATION | M13: TOTAL PRICE | Q13: =SUM(Q3:Q12) -> 0
A14: 45612 | B14: Kingspor Grinding Disc 4.5" (111x6 mm ) | C14: 601101840003 | D14: 45612 | E14: Kingspor Grinding Disc 4.5" (111x6 mm ) | F14: PCS | G14: 4.5 | H14: AL BAHAR DN-15238 | I14: STEEL FABRICATION CON | J14: STEEL FABRICATION | M14: CARPENTER
A15: 45612 | B15: STEEL TUBE 19X19X1.5MM | C15: 401101840493 | D15: 45612 | E15: STEEL TUBE 19X19X1.5MM | F15: PCS | G15: 14.9 | H15: QATAR STEEL DN-76178 | I15: STEEL FABRICATION | J15: STEEL FABRICATION | M15: DATE OF DELIVERY | N15: ITEM DESCRIPTION | O15: UNIT PRICE | P15: QTY | Q15: TOTAL PRICE
A16: 45594 | B16: Cutting Disk 14" | C16: 091101840003 | D16: 45594 | E16: Cutting Disk 14" | F16: PCS | G16: 16 | H16: AL ABDULLA TRDG DN-21971 | I16: STEEL FABRICATION CON | J16: STEEL FABRICATION | M16: =IFERROR(VLOOKUP(N16,$B$3:$G$508,3,0),0) -> 0 | O16: =IFERROR(VLOOKUP(N16,$B$3:$G$246,6,0),0) -> 0 | Q16: =PRODUCT(O16,P16) -> 0
A17: 45571 | B17: Flat Bar 40x4x6mtr | C17: 521101840016 | D17: 45571 | E17: Flat Bar 40x4x6mtr | F17: PCS | G17: 22.5 | H17: QATAR STEEL INV 37153 | I17: STEEL FABRICATION | J17: STEEL FABRICATION | M17: =IFERROR(VLOOKUP(N17,$B$3:$G$508,3,0),0) -> 0 | O17: =IFERROR(VLOOKUP(N17,$B$3:$G$246,6,0),0) -> 0 | Q17: =PRODUCT(O17,P17) -> 0
A18: 45556 | B18: G.I Pipe 4"X2mmX6m | C18: 521101840015 | D18: 45556 | E18: G.I Pipe 4"X2mmX6m | F18: PCS | G18: 106 | H18: QATAR STEEL INV 499698 AND 499699 | I18: STEEL FABRICATION | J18: STEEL FABRICATION | M18: =IFERROR(VLOOKUP(N18,$B$3:$G$508,3,0),0) -> 0 | O18: =IFERROR(VLOOKUP(N18,$B$3:$G$246,6,0),0) -> 0 | Q18: =PRODUCT(O18,P18) -> 0
A19: 45554 | B19: Concrete Drill Bit 6mmX110 | C19: 621101840006 | D19: 45554 | E19: Concrete Drill Bit 6mmX110 | F19: PCS | G19: 6 | H19: AL BAHAR DN-15009 | I19: STEEL FABRICATION CON | J19: STEEL FABRICATION | M19: =IFERROR(VLOOKUP(N19,$B$3:$G$508,3,0),0) -> 0 | O19: =IFERROR(VLOOKUP(N19,$B$3:$G$246,6,0),0) -> 0 | Q19: =PRODUCT(O19,P19) -> 0
A20: 45551 | B20: Round Bar 12mmX6mtr | C20: 521101840012 | D20: 45551 | E20: Round Bar 12mmX6mtr | F20: PCS | G20: 17.5 | H20: AL ITTEFAQ TRDG INV 13830 | I20: STEEL FABRICATION | J20: STEEL FABRICATION | M20: =IFERROR(VLOOKUP(N20,$B$3:$G$508,3,0),0) -> 0 | O20: =IFERROR(VLOOKUP(N20,$B$3:$G$246,6,0),0) -> 0 | Q20: =PRODUCT(O20,P20) -> 0
A21: 45533 | B21: G.I Pipe ½"X2mmX6m | C21: 521101840014 | D21: 45533 | E21: G.I Pipe ½"X2mmX6m | F21: PCS | G21: 23 | H21: AL - ITTEFAQ STEEL INV NO-12991 | I21: STEEL FABRICATION | J21: STEEL FABRICATION | M21: =IFERROR(VLOOKUP(N21,$B$3:$G$508,3,0),0) -> 0 | O21: =IFERROR(VLOOKUP(N21,$B$3:$G$246,6,0),0) -> 0 | Q21: =PRODUCT(O21,P21) -> 0
A22: 45533 | B22: STEEL TUBE 50X50X2MM | C22: 401101840412 | D22: 45533 | E22: STEEL TUBE 50X50X2MM | F22: Pcs | G22: 40.5 | H22: QATAR STEEL INV NO- 495936 | I22: STEEL FABRICATION | J22: STEEL FABRICATION | M22: =IFERROR(VLOOKUP(N22,$B$3:$G$508,3,0),0) -> 0 | O22: =IFERROR(VLOOKUP(N22,$B$3:$G$246,6,0),0) -> 0 | Q22: =PRODUCT(O22,P22) -> 0
A23: 45500 | B23: MS Tube 50X50X2.0mm | C23: 521101840009 | D23: 45500 | E23: MS Tube 50X50X2.0mm | F23: PCS | G23: 54 | H23: Qatar Steel DN N0 - 71811 | I23: STEEL FABRICATION | J23: STEEL FABRICATION | M23: =IFERROR(VLOOKUP(N23,$B$3:$G$508,3,0),0) -> 0 | O23: =IFERROR(VLOOKUP(N23,$B$3:$G$246,6,0),0) -> 0 | Q23: =PRODUCT(O23,P23) -> 0
A24: 45486 | B24: Rec.Angle Tube 50x25x1.5mm | C24: 401101840516 | D24: 45486 | E24: Rec.Angle Tube 50x25x1.5mm | F24: PCS | G24: 30.2 | H24: QATAR STEEL DN NO- 71517 | I24: STEEL FABRICATION | J24: STEEL FABRICATION | M24: =IFERROR(VLOOKUP(N24,$B$3:$G$508,3,0),0) -> 0 | O24: =IFERROR(VLOOKUP(N24,$B$3:$G$246,6,0),0) -> 0 | Q24: =PRODUCT(O24,P24) -> 0
A25: 45484 | B25: Cutting Disk 9 " | C25: 091101840001 | D25: 45484 | E25: Cutting Disk 9 " | F25: PCS | G25: 7 | H25: AL- ABDULLA TRD&CO. DN NO- 21739 | I25: STEEL FABRICATION CON | J25: STEEL FABRICATION | M25: =IFERROR(VLOOKUP(N25,$B$3:$G$508,3,0),0) -> 0 | O25: =IFERROR(VLOOKUP(N25,$B$3:$G$246,6,0),0) -> 0 | Q25: =PRODUCT(O25,P25) -> 0
A26: 45470 | B26: Steel Flat Bar 16X3mm | C26: 401101840453 | D26: 45470 | E26: Steel Flat Bar 16X3mm | F26: PCS | G26: 9 | H26: AL ITEFAQ STEEL INV -09851 | I26: STEEL FABRICATION | J26: STEEL FABRICATION | M26: TOTAL PRICE | Q26: =SUM(Q16:Q25) -> 0
A27: 45437 | B27: Round Bar 10mm | C27: 401101840475 | D27: 45437 | E27: Round Bar 10mm | F27: Pcs | G27: 15 | H27: AL ITTEFAQ INV 24-08196 | I27: STEEL FABRICATION | J27: STEEL FABRICATION | M27: FOAM AND ACRYLIC AND FOREX WORK
A28: 45428 | B28: Steel Tube 12x12x1.2mm | C28: 401101840452 | D28: 45428 | E28: Steel Tube 12x12x1.2mm | F28: PCS | G28: 10 | H28: AL ITTEFAQ INV 24-07674 | I28: STEEL FABRICATION | J28: STEEL FABRICATION | M28: DATE OF DELIVERY | N28: ITEM DESCRIPTION | O28: UNIT PRICE | P28: QTY | Q28: TOTAL PRICE
A29: 45428 | B29: Hand Glows Leather Full Sleave HD | C29: 571101840001 | D29: 45428 | E29: Hand Glows Leather Full Sleave HD | F29: PAIR | G29: 10 | H29: AL ABDULLA TRDG DN-20485 | I29: STEEL FABRICATION CON | J29: STEEL FABRICATION | M29: =IFERROR(VLOOKUP(N29,$B$3:$G$508,3,0),0) -> 0 | O29: =IFERROR(VLOOKUP(N29,$B$3:$G$246,6,0),0) -> 0 | Q29: =PRODUCT(O29,P29) -> 0
A30: 45409 | B30: Hand Glows Leather - HG1101 | C30: 401131910006 | D30: 45409 | E30: Hand Glows Leather - HG1101 | F30: PAR | G30: 3.8 | H30: AL-ABDULLA TRD.CO. DN NO- 20714 | I30: STEEL FABRICATION CON | J30: STEEL FABRICATION | M30: =IFERROR(VLOOKUP(N30,$B$3:$G$508,3,0),0) -> 0 | O30: =IFERROR(VLOOKUP(N30,$B$3:$G$246,6,0),0) -> 0 | Q30: =PRODUCT(O30,P30) -> 0
A31: 45383 | B31: Flat Bar 16x8x6m | C31: 521101840006 | D31: 45383 | E31: Flat Bar 16x8x6m | F31: PCS | G31: 24 | H31: AL ITTEFAQ INV 24-05316 | I31: STEEL FABRICATION | J31: STEEL FABRICATION | M31: =IFERROR(VLOOKUP(N31,$B$3:$G$508,3,0),0) -> 0 | O31: =IFERROR(VLOOKUP(N31,$B$3:$G$246,6,0),0) -> 0 | Q31: =PRODUCT(O31,P31) -> 0
A32: 45383 | B32: GI PIPE 1"X2MM - 6MTR | C32: 521101840002 | D32: 45383 | E32: GI PIPE 1"X2MM - 6MTR | F32: PCS | G32: 40 | H32: AL ITTEFAQ INV 24-05316 | I32: STEEL FABRICATION | J32: STEEL FABRICATION | M32: =IFERROR(VLOOKUP(N32,$B$3:$G$508,3,0),0) -> 0 | O32: =IFERROR(VLOOKUP(N32,$B$3:$G$246,6,0),0) -> 0 | Q32: =PRODUCT(O32,P32) -> 0
A33: 45307 | B33: Makita Cutting Disc 4.5" (115x1.2mm) | C33: 601101840001 | D33: 45307 | E33: Makita Cutting Disc 4.5" (115x1.2mm) | F33: PCS | G33: 3 | H33: AL BAHAR DN-13436 | I33: STEEL FABRICATION CON | J33: STEEL FABRICATION | M33: =IFERROR(VLOOKUP(N33,$B$3:$G$508,3,0),0) -> 0 | O33: =IFERROR(VLOOKUP(N33,$B$3:$G$246,6,0),0) -> 0 | Q33: =PRODUCT(O33,P33) -> 0
A34: 45305 | B34: STEEL PIPE ¾"x1.5mm | C34: 401101840441 | D34: 45305 | E34: STEEL PIPE ¾"x1.5mm | F34: Pcs | G34: 20 | H34: QATAR STEEL DN-67716 | I34: STEEL FABRICATION | J34: STEEL FABRICATION | M34: =IFERROR(VLOOKUP(N34,$B$3:$G$508,3,0),0) -> 0 | O34: =IFERROR(VLOOKUP(N34,$B$3:$G$246,6,0),0) -> 0 | Q34: =PRODUCT(O34,P34) -> 0
A35: 45300 | B35: G.I Pipe 2"X1.5mm | C35: 521101840011 | D35: 45300 | E35: G.I Pipe 2"X1.5mm | F35: DRM | G35: 45 | H35: QATAR STEEL DN-67586 | I35: STEEL FABRICATION | J35: STEEL FABRICATION | M35: =IFERROR(VLOOKUP(N35,$B$3:$G$508,3,0),0) -> 0 | O35: =IFERROR(VLOOKUP(N35,$B$3:$G$246,6,0),0) -> 0 | Q35: =PRODUCT(O35,P35) -> 0
A36: 45638 | B36: Screw 3" x8 black - (250/300 Pkt) | C36: 401101840025 | D36: 45638 | E36: Screw 3" x8 black - (250/300 Pkt) | F36: PKT | G36: 17.5 | H36: AL ABDULLA TRDG DN-22834 | I36: CARPENTER CON | J36: CARPENTER | M36: =IFERROR(VLOOKUP(N36,$B$3:$G$508,3,0),0) -> 0 | O36: =IFERROR(VLOOKUP(N36,$B$3:$G$246,6,0),0) -> 0 | Q36: =PRODUCT(O36,P36) -> 0
A37: 45638 | B37: Brad Nail Billionaire - F 20 (5000/Pkt) | C37: 581101840004 | D37: 45638 | E37: Brad Nail Billionaire - F 20 (5000/Pkt) | F37: PKT | G37: 12 | H37: AL ABDULLA TRDG DN-22834 | I37: CARPENTER CON | J37: CARPENTER | M37: =IFERROR(VLOOKUP(N37,$B$3:$G$508,3,0),0) -> 0 | O37: =IFERROR(VLOOKUP(N37,$B$3:$G$246,6,0),0) -> 0 | Q37: =PRODUCT(O37,P37) -> 0
A38: 45636 | B38: Makita Hss Dril Bit 4mm | C38: 401101910004 | D38: 45636 | E38: Makita Hss Dril Bit 4mm | F38: PCS | G38: 2.75 | H38: AL ABDUULLA DN NO- 22831 | I38: CARPENTER CON | J38: CARPENTER | M38: =IFERROR(VLOOKUP(N38,$B$3:$G$508,3,0),0) -> 0 | O38: =IFERROR(VLOOKUP(N38,$B$3:$G$246,6,0),0) -> 0 | Q38: =PRODUCT(O38,P38) -> 0
A39: 45636 | B39: STEEL SCREW HEX WASHER HEAD 4X14 | C39: 401101840450 | D39: 45636 | E39: STEEL SCREW HEX WASHER HEAD 4X14 | F39: PCS | G39: 46 | H39: AL ABDUULLA DN NO- 22831 | I39: CARPENTER CON | J39: CARPENTER | M39: TOTAL PRICE | Q39: =SUM(Q29:Q38) -> 0
A40: 45636 | B40: Exwell N3 Silicone Sealant | C40: 401101840528 | D40: 45636 | E40: Exwell N3 Silicone Sealant | F40: PCS | G40: 13.33 | H40: AL BAHAR DN NO-16042 | I40: CARPENTER CON | J40: CARPENTER | M40: GENERAL WORK
A41: 45635 | B41: Commercial Plywood 4x8x9mm - Malaysia - KP09 | C41: 401101840246 | D41: 45635 | E41: Commercial Plywood 4x8x9mm - Malaysia - KP09 | F41: SHT | G41: 45 | H41: BBMC DN-11737 | I41: CARPENTER | J41: CARPENTER | M41: DATE OF DELIVERY | N41: ITEM DESCRIPTION | O41: UNIT PRICE | P41: QTY | Q41: TOTAL PRICE
A42: 45633 | B42: Fibre Board(MDF) - 4x8x12MM - MD12 | C42: 401101840224 | D42: 45633 | E42: Fibre Board(MDF) - 4x8x12MM - MD12 | F42: SHT | G42: 39 | H42: BBMC DN-24201443 | I42: CARPENTER | J42: CARPENTER | M42: =IFERROR(VLOOKUP(N42,$B$3:$G$508,3,0),0) -> 0 | O42: =IFERROR(VLOOKUP(N42,$B$3:$G$246,6,0),0) -> 0 | Q42: =PRODUCT(O42,P42) -> 0
A43: 45633 | B43: Fibre Board(MDF) - 4x8x6MM - MD06 | C43: 401091620005 | D43: 45633 | E43: Fibre Board(MDF) - 4x8x6MM - MD06 | F43: SHT | G43: 20 | H43: BBMC DN-24201443 | I43: CARPENTER | J43: CARPENTER | M43: =IFERROR(VLOOKUP(N43,$B$3:$G$508,3,0),0) -> 0 | O43: =IFERROR(VLOOKUP(N43,$B$3:$G$246,6,0),0) -> 0 | Q43: =PRODUCT(O43,P43) -> 0
A44: 45631 | B44: Jigsaw Blade T244D - Bosch | C44: 401101840373 | D44: 45631 | E44: Jigsaw Blade T244D - Bosch | F44: Pkt | G44: 18 | H44: AL ABDULLA TRDG DN-22817 | I44: CARPENTER CON | J44: CARPENTER | M44: =IFERROR(VLOOKUP(N44,$B$3:$G$508,3,0),0) -> 0 | O44: =IFERROR(VLOOKUP(N44,$B$3:$G$246,6,0),0) -> 0 | Q44: =PRODUCT(O44,P44) -> 0
A45: 45631 | B45: Makita staples 10x10mm (5000/Pkt) | C45: 401101840016 | D45: 45631 | E45: Makita staples 10x10mm (5000/Pkt) | F45: PKT | G45: 29.5 | H45: AL ABDULLA TRDG DN-22817 | I45: CARPENTER CON | J45: CARPENTER | M45: =IFERROR(VLOOKUP(N45,$B$3:$G$508,3,0),0) -> 0 | O45: =IFERROR(VLOOKUP(N45,$B$3:$G$246,6,0),0) -> 0 | Q45: =PRODUCT(O45,P45) -> 0
A46: 45631 | B46: Stapler Pin 80008 - (10000Pcs) | C46: 401101840112 | D46: 45631 | E46: Stapler Pin 80008 - (10000Pcs) | F46: Box | G46: 16 | H46: AL ABDULLA TRDG DN-22817 | I46: CARPENTER CON | J46: CARPENTER | M46: =IFERROR(VLOOKUP(N46,$B$3:$G$508,3,0),0) -> 0 | O46: =IFERROR(VLOOKUP(N46,$B$3:$G$246,6,0),0) -> 0 | Q46: =PRODUCT(O46,P46) -> 0
A47: 45631 | B47: Screw 2" x6 black (500Pcs/Pkt) | C47: 401101840008 | D47: 45631 | E47: Screw 2" x6 black (500Pcs/Pkt) | F47: PKT | G47: 17 | H47: AL ABDULLA TRDG DN-22817 | I47: CARPENTER CON | J47: CARPENTER | M47: =IFERROR(VLOOKUP(N47,$B$3:$G$508,3,0),0) -> 0 | O47: =IFERROR(VLOOKUP(N47,$B$3:$G$246,6,0),0) -> 0 | Q47: =PRODUCT(O47,P47) -> 0
A48: 45631 | B48: Makita Brad Nails 18GA/15 (5000Pcs/Pkt) | C48: 401101840036 | D48: 45631 | E48: Makita Brad Nails 18GA/15 (5000Pcs/Pkt) | F48: PKT | G48: 12 | H48: AL ABDULLA TRDG DN-22817 | I48: CARPENTER CON | J48: CARPENTER | M48: =IFERROR(VLOOKUP(N48,$B$3:$G$508,3,0),0) -> 0 | O48: =IFERROR(VLOOKUP(N48,$B$3:$G$246,6,0),0) -> 0 | Q48: =PRODUCT(O48,P48) -> 0
A49: 45631 | B49: Makita Brad Nails 18GA/25 (5000Pcs/Pkt) | C49: 401101840037 | D49: 45631 | E49: Makita Brad Nails 18GA/25 (5000Pcs/Pkt) | F49: PKT | G49: 14 | H49: AL ABDULLA TRDG DN-22817 | I49: CARPENTER CON | J49: CARPENTER | M49: =IFERROR(VLOOKUP(N49,$B$3:$G$508,3,0),0) -> 0 | O49: =IFERROR(VLOOKUP(N49,$B$3:$G$246,6,0),0) -> 0 | Q49: =PRODUCT(O49,P49) -> 0
A50: 45631 | B50: Brad Nail Billionaire - F 15 (5000/Pkt) (F 50) | C50: 581101840005 | D50: 45631 | E50: Brad Nail Billionaire - F 15 (5000/Pkt) (F 50) | F50: PKT | G50: 12 | H50: AL BAHAR DN-16028 | I50: CARPENTER CON | J50: CARPENTER | M50: =IFERROR(VLOOKUP(N50,$B$3:$G$508,3,0),0) -> 0 | O50: =IFERROR(VLOOKUP(N50,$B$3:$G$246,6,0),0) -> 0 | Q50: =PRODUCT(O50,P50) -> 0
A51: 45631 | B51: Brad Nail Billionaire - F 25 (5000/Pkt) | C51: 581101840003 | D51: 45631 | E51: Brad Nail Billionaire - F 25 (5000/Pkt) | F51: PKT | G51: 14 | H51: AL BAHAR DN-16028 | I51: CARPENTER CON | J51: CARPENTER | M51: =IFERROR(VLOOKUP(N51,$B$3:$G$508,3,0),0) -> 0 | O51: =IFERROR(VLOOKUP(N51,$B$3:$G$246,6,0),0) -> 0 | Q51: =PRODUCT(O51,P51) -> 0
A52: 45631 | B52: Cable Tie 450 X 7.6mm | C52: 401101840432 | D52: 45631 | E52: Cable Tie 450 X 7.6mm | F52: Pkt | G52: 19 | H52: TDC DN-116 | I52: CARPENTER CON | J52: CARPENTER | M52: TOTAL PRICE | Q52: =SUM(Q42:Q51) -> 0
A53: 45629 | B53: Screw ¾" x6 Black (1000Pcs/Pkt) | C53: 401101840029 | D53: 45629 | E53: Screw ¾" x6 Black (1000Pcs/Pkt) | F53: PKT | G53: 16 | H53: AL BAHAR DN NO- 16023 | I53: CARPENTER CON | J53: CARPENTER | M53: PAINTER
A54: 45629 | B54: Self Drilling Screw 8x¾" - 1000 pcs | C54: 401101840227 | D54: 45629 | E54: Self Drilling Screw 8x¾" - 1000 pcs | F54: Pkt | G54: 30 | H54: AL BAHAR DN NO- 16023 | I54: CARPENTER CON | J54: CARPENTER | M54: DATE OF DELIVERY | N54: ITEM DESCRIPTION | O54: UNIT PRICE | P54: QTY | Q54: TOTAL PRICE
A55: 45628 | B55: Steel Screw 4"X14 | C55: 401101840482 | D55: 45628 | E55: Steel Screw 4"X14 | F55: Pkt | G55: 46 | H55: AL ABDULLA TRDG DN-22811 | I55: CARPENTER CON | J55: CARPENTER | M55: =IFERROR(VLOOKUP(N55,$B$3:$G$508,3,0),0) -> 0 | O55: =IFERROR(VLOOKUP(N55,$B$3:$G$246,6,0),0) -> 0 | Q55: =PRODUCT(O55,P55) -> 0
A56: 45627 | B56: Austrian White Wood -morabaa- 2x2x13 - AW22 | C56: 401091620007 | D56: 45627 | E56: Austrian White Wood -morabaa- 2x2x13 - AW22 | F56: Pcs | G56: 11 | H56: GRAND STORE DN-112390 | I56: CARPENTER | J56: CARPENTER | M56: =IFERROR(VLOOKUP(N56,$B$3:$G$508,3,0),0) -> 0 | O56: =IFERROR(VLOOKUP(N56,$B$3:$G$246,6,0),0) -> 0 | Q56: =PRODUCT(O56,P56) -> 0
A57: 45625 | B57: CNC Bit D4.0 L22/1 Wood | C57: 621101840028 | D57: 45625 | E57: CNC Bit D4.0 L22/1 Wood | F57: PCS | G57: 34 | H57: MRM INV 12019 | I57: CARPENTER CON | J57: CARPENTER | M57: =IFERROR(VLOOKUP(N57,$B$3:$G$508,3,0),0) -> 0 | O57: =IFERROR(VLOOKUP(N57,$B$3:$G$246,6,0),0) -> 0 | Q57: =PRODUCT(O57,P57) -> 0
A58: 45624 | B58: Self Drilling Screw 1"X6 Patta | C58: 401101840289 | D58: 45624 | E58: Self Drilling Screw 1"X6 Patta | F58: PKT | G58: 26 | H58: AL BAHAR DN-16016 | I58: CARPENTER CON | J58: CARPENTER | M58: =IFERROR(VLOOKUP(N58,$B$3:$G$508,3,0),0) -> 0 | O58: =IFERROR(VLOOKUP(N58,$B$3:$G$246,6,0),0) -> 0 | Q58: =PRODUCT(O58,P58) -> 0
A59: 45624 | B59: Screw Bit Patta - 2 - 26 | C59: 401101840301 | D59: 45624 | E59: Screw Bit Patta - 2 - 26 | F59: Pcs | G59: 3 | H59: AL BAHAR DN-16016 | I59: CARPENTER CON | J59: CARPENTER | M59: =IFERROR(VLOOKUP(N59,$B$3:$G$508,3,0),0) -> 0 | O59: =IFERROR(VLOOKUP(N59,$B$3:$G$246,6,0),0) -> 0 | Q59: =PRODUCT(O59,P59) -> 0
A60: 45624 | B60: Poly Fix Glue | C60: 401101840368 | D60: 45624 | E60: Poly Fix Glue | F60: Gal | G60: 37 | H60: AL ABDULLA TRDG DN-22804 | I60: CARPENTER CON | J60: CARPENTER | M60: =IFERROR(VLOOKUP(N60,$B$3:$G$508,3,0),0) -> 0 | O60: =IFERROR(VLOOKUP(N60,$B$3:$G$246,6,0),0) -> 0 | Q60: =PRODUCT(O60,P60) -> 0
A61: 45620 | B61: Makita Hss Dril Bit 20mm | C61: 401101840507 | D61: 45620 | E61: Makita Hss Dril Bit 20mm | F61: PCS | G61: 39 | H61: AL ABDULLA TRDG DN-22138 | I61: CARPENTER CON | J61: CARPENTER | M61: =IFERROR(VLOOKUP(N61,$B$3:$G$508,3,0),0) -> 0 | O61: =IFERROR(VLOOKUP(N61,$B$3:$G$246,6,0),0) -> 0 | Q61: =PRODUCT(O61,P61) -> 0
A62: 45619 | B62: Makita Hss Dril Bit 10mm | C62: 401101910010 | D62: 45619 | E62: Makita Hss Dril Bit 10mm | F62: PCS | G62: 19 | H62: AL ABDULLA TRDG DN-22140 | I62: CARPENTER CON | J62: CARPENTER | M62: =IFERROR(VLOOKUP(N62,$B$3:$G$508,3,0),0) -> 0 | O62: =IFERROR(VLOOKUP(N62,$B$3:$G$246,6,0),0) -> 0 | Q62: =PRODUCT(O62,P62) -> 0
A63: 45616 | B63: Double Side Tape For Acrylic 2" | C63: 401101840312 | D63: 45616 | E63: Double Side Tape For Acrylic 2" | F63: PCS | G63: 60 | H63: HO | I63: CARPENTER CON | J63: CARPENTER | M63: =IFERROR(VLOOKUP(N63,$B$3:$G$508,3,0),0) -> 0 | O63: =IFERROR(VLOOKUP(N63,$B$3:$G$246,6,0),0) -> 0 | Q63: =PRODUCT(O63,P63) -> 0
A64: 45615 | B64: Fevicol - 50Kg | C64: 401101840097 | D64: 45615 | E64: Fevicol - 50Kg | F64: DRM | G64: 540 | H64: AL ABDULLA TRDG DN-22134 | I64: CARPENTER CON | J64: CARPENTER | M64: =IFERROR(VLOOKUP(N64,$B$3:$G$508,3,0),0) -> 0 | O64: =IFERROR(VLOOKUP(N64,$B$3:$G$246,6,0),0) -> 0 | Q64: =PRODUCT(O64,P64) -> 0
A65: 45615 | B65: Self Drilling Screw 2X8mm - 500/Pkt | C65: 401101840354 | D65: 45615 | E65: Self Drilling Screw 2X8mm - 500/Pkt | F65: Pkt | G65: 29 | H65: AL ABDULLA TRDG DN-22134 | I65: CARPENTER CON | J65: CARPENTER | M65: TOTAL PRICE | Q65: =SUM(Q55:Q64) -> 0
A66: 45615 | B66: Self Drilling Screw 1½" X6mm | C66: 401101840253 | D66: 45615 | E66: Self Drilling Screw 1½" X6mm | F66: PKT | G66: 33 | H66: AL ABDULLA TRDG DN-22134 | I66: CARPENTER CON | J66: CARPENTER | M66: PARKE (VINYL)
A67: 45615 | B67: Steel Screw 1"X14 500 PCS | C67: 401101840384 | D67: 45615 | E67: Steel Screw 1"X14 500 PCS | F67: PKT | G67: 48 | H67: AL ABDULLA TRDG DN-22134 | I67: CARPENTER CON | J67: CARPENTER | M67: DATE OF DELIVERY | N67: ITEM DESCRIPTION | O67: UNIT PRICE | P67: QTY | Q67: TOTAL PRICE
A68: 45614 | B68: Jigsaw Blade T101B - Bosch | C68: 401101840298 | D68: 45614 | E68: Jigsaw Blade T101B - Bosch | F68: PKT | G68: 17 | H68: AL BAHAR DN-15246 | I68: CARPENTER CON | J68: CARPENTER | M68: =IFERROR(VLOOKUP(N68,$B$3:$G$508,3,0),0) -> 0 | O68: =IFERROR(VLOOKUP(N68,$B$3:$G$508,6,0),0) -> 0 | Q68: =PRODUCT(O68,P68) -> 0
A69: 45614 | B69: Router Bit 13x8mm | C69: 401101840532 | D69: 45614 | E69: Router Bit 13x8mm | F69: PCS | G69: 25 | H69: AL BAHAR DN-15246 | I69: CARPENTER CON | J69: CARPENTER | M69: =IFERROR(VLOOKUP(N69,$B$3:$G$508,3,0),0) -> 0 | O69: =IFERROR(VLOOKUP(N69,$B$3:$G$508,6,0),0) -> 0 | Q69: =PRODUCT(O69,P69) -> 0
A70: 45613 | B70: CNC Bit D3 Wood 3mm | C70: 621101840026 | D70: 45613 | E70: CNC Bit D3 Wood 3mm | F70: PCS | G70: 30 | H70: MRM INV 894739 | I70: CARPENTER CON | J70: CARPENTER | M70: =IFERROR(VLOOKUP(N70,$B$3:$G$508,3,0),0) -> 0 | O70: =IFERROR(VLOOKUP(N70,$B$3:$G$508,6,0),0) -> 0 | Q70: =PRODUCT(O70,P70) -> 0
A71: 45612 | B71: Screw 1½" x6 black (250pcs/Pkt) | C71: 401101840007 | D71: 45612 | E71: Screw 1½" x6 black (250pcs/Pkt) | F71: PKT | G71: 14.75 | H71: AL BAHAR DN-15238 | I71: CARPENTER CON | J71: CARPENTER | M71: =IFERROR(VLOOKUP(N71,$B$3:$G$508,3,0),0) -> 0 | O71: =IFERROR(VLOOKUP(N71,$B$3:$G$508,6,0),0) -> 0 | Q71: =PRODUCT(O71,P71) -> 0
A72: 45609 | B72: Screw 1½" x6 black (500pcs/Pkt) | C72: 401101840155 | D72: 45609 | E72: Screw 1½" x6 black (500pcs/Pkt) | F72: Box | G72: 14.75 | H72: AL ABDULLA DN NO-22120 | I72: CARPENTER CON | J72: CARPENTER | M72: =IFERROR(VLOOKUP(N72,$B$3:$G$508,3,0),0) -> 0 | O72: =IFERROR(VLOOKUP(N72,$B$3:$G$508,6,0),0) -> 0 | Q72: =PRODUCT(O72,P72) -> 0
A73: 45608 | B73: Fevicol 1K Pur Adhesive 500g | C73: 641101840001 | D73: 45608 | E73: Fevicol 1K Pur Adhesive 500g | F73: PCS | G73: 32 | H73: AL BAHAR DN-14680 | I73: CARPENTER CON | J73: CARPENTER | M73: =IFERROR(VLOOKUP(N73,$B$3:$G$508,3,0),0) -> 0 | O73: =IFERROR(VLOOKUP(N73,$B$3:$G$508,6,0),0) -> 0 | Q73: =PRODUCT(O73,P73) -> 0
A74: 45606 | B74: Router bit 6x8 mm With Bearing | C74: 621101840001 | D74: 45606 | E74: Router bit 6x8 mm With Bearing | F74: PCS | G74: 16 | H74: AL BAHAR DN-15232 | I74: CARPENTER CON | J74: CARPENTER | M74: =IFERROR(VLOOKUP(N74,$B$3:$G$508,3,0),0) -> 0 | O74: =IFERROR(VLOOKUP(N74,$B$3:$G$508,6,0),0) -> 0 | Q74: =PRODUCT(O74,P74) -> 0
A75: 45602 | B75: Fibre Board (MDF) 16MM | C75: 401101840460 | D75: 45602 | E75: Fibre Board (MDF) 16MM | F75: SHT | G75: 46 | H75: BBMC DN-24201222 | I75: CARPENTER | J75: CARPENTER | M75: =IFERROR(VLOOKUP(N75,$B$3:$G$508,3,0),0) -> 0 | O75: =IFERROR(VLOOKUP(N75,$B$3:$G$508,6,0),0) -> 0 | Q75: =PRODUCT(O75,P75) -> 0
A76: 45601 | B76: Fibre Board (MDF) 4x8x 9mm - MD09 | C76: 401091620016 | D76: 45601 | E76: Fibre Board (MDF) 4x8x 9mm - MD09 | F76: SHT | G76: 28 | H76: BBMC DN-24201168 | I76: CARPENTER | J76: CARPENTER | M76: =IFERROR(VLOOKUP(N76,$B$3:$G$508,3,0),0) -> 0 | O76: =IFERROR(VLOOKUP(N76,$B$3:$G$508,6,0),0) -> 0 | Q76: =PRODUCT(O76,P76) -> 0
A77: 45594 | B77: Polycarbonate Sheet clear Obscure 2.5mm | C77: 401101840483 | D77: 45594 | E77: Polycarbonate Sheet clear Obscure 2.5mm | F77: SHT | G77: 350 | H77: SABIN PLASTIC DN-SQDO2404477,SQDO2404435 | I77: CARPENTER | J77: CARPENTER | M77: =IFERROR(VLOOKUP(N77,$B$3:$G$508,3,0),0) -> 0 | O77: =IFERROR(VLOOKUP(N77,$B$3:$G$508,6,0),0) -> 0 | Q77: =PRODUCT(O77,P77) -> 0
A78: 45594 | B78: Makita Brad Nails 18GA/30 (5000Pcs/Pkt) | C78: 401101840035 | D78: 45594 | E78: Makita Brad Nails 18GA/30 (5000Pcs/Pkt) | F78: PKT | G78: 16.5 | H78: AL ABDULLA TRDG DN-21971 | I78: CARPENTER CON | J78: CARPENTER | M78: TOTAL PRICE | Q78: =SUM(Q68:Q77) -> 0
A79: 45594 | B79: Jigsaw Blade - T144D Bosch | C79: 401101840372 | D79: 45594 | E79: Jigsaw Blade - T144D Bosch | F79: Pkt | G79: 18 | H79: AL ABDULLA TRDG DN-21971 | I79: CARPENTER CON | J79: CARPENTER
A80: 45594 | B80: Brad Nail Billionaire - F 30 (5000/Pkt) | C80: 581101840002 | D80: 45594 | E80: Brad Nail Billionaire - F 30 (5000/Pkt) | F80: PKT | G80: 15 | H80: AL BAHAR DN-15205 | I80: CARPENTER CON | J80: CARPENTER | M80: FABRIC
A81: 45590 | B81: Dry Wall Tapping Screw (Steel) ¾X6 (1000 Pcs) | C81: 420300390004 | D81: 45590 | E81: Dry Wall Tapping Screw (Steel) ¾X6 (1000 Pcs) | F81: PKT | G81: 19 | H81: AL ABDULLA TRDG DN-17219 | I81: CARPENTER CON | J81: CARPENTER | M81: DATE OF DELIVERY | N81: ITEM DESCRIPTION | O81: UNIT PRICE | P81: QTY | Q81: TOTAL PRICE
A82: 45582 | B82: Steel Screw Hex Washer 3X14 - 250Pcs | C82: 401101840455 | D82: 45582 | E82: Steel Screw Hex Washer 3X14 - 250Pcs | F82: Pkt | G82: 47 | H82: AL ABDULLA TRDN DN-21827 | I82: CARPENTER CON | J82: CARPENTER | M82: =IFERROR(VLOOKUP(N82,$B$3:$G$508,3,0),0) -> 0 | O82: =IFERROR(VLOOKUP(N82,$B$3:$G$508,6,0),0) -> 0 | Q82: =PRODUCT(O82,P82) -> 0
A83: 45581 | B83: Black Screw 1¼X6 (1000/Pkt) | C83: 401101840518 | D83: 45581 | E83: Black Screw 1¼X6 (1000/Pkt) | F83: PKT | G83: 32 | H83: AL BAHAR DN NO- 15138 | I83: CARPENTER CON | J83: CARPENTER | M83: =IFERROR(VLOOKUP(N83,$B$3:$G$508,3,0),0) -> 0 | O83: =IFERROR(VLOOKUP(N83,$B$3:$G$508,6,0),0) -> 0 | Q83: =PRODUCT(O83,P83) -> 0
A84: 45581 | B84: Screw Bit PH2 ¾"X80 | C84: 621101840022 | D84: 45581 | E84: Screw Bit PH2 ¾"X80 | F84: PCS | G84: 3.5 | H84: AL BAHAR DN NO- 15138 | I84: CARPENTER CON | J84: CARPENTER | M84: =IFERROR(VLOOKUP(N84,$B$3:$G$508,3,0),0) -> 0 | O84: =IFERROR(VLOOKUP(N84,$B$3:$G$508,6,0),0) -> 0 | Q84: =PRODUCT(O84,P84) -> 0
A85: 45571 | B85: Router Bit 3mmx8mm - Normal | C85: 621101840009 | D85: 45571 | E85: Router Bit 3mmx8mm - Normal | F85: PCS | G85: 25 | H85: AL BAHAR DN NO- 15101 | I85: CARPENTER CON | J85: CARPENTER | M85: =IFERROR(VLOOKUP(N85,$B$3:$G$508,3,0),0) -> 0 | O85: =IFERROR(VLOOKUP(N85,$B$3:$G$508,6,0),0) -> 0 | Q85: =PRODUCT(O85,P85) -> 0
A86: 45566 | B86: Screw 4" x10 black (200/pkt) | C86: 401101840010 | D86: 45566 | E86: Screw 4" x10 black (200/pkt) | F86: PKT | G86: 29 | H86: AL BAHAR DN NO 15039 | I86: CARPENTER CON | J86: CARPENTER | M86: =IFERROR(VLOOKUP(N86,$B$3:$G$508,3,0),0) -> 0 | O86: =IFERROR(VLOOKUP(N86,$B$3:$G$508,6,0),0) -> 0 | Q86: =PRODUCT(O86,P86) -> 0
A87: 45566 | B87: Screw 4" x10 black (250/pkt) | C87: 401101840026 | D87: 45566 | E87: Screw 4" x10 black (250/pkt) | F87: PKT | G87: 29 | H87: AL ABDULLA TRDG DN-22622 | I87: CARPENTER CON | J87: CARPENTER | M87: =IFERROR(VLOOKUP(N87,$B$3:$G$508,3,0),0) -> 0 | O87: =IFERROR(VLOOKUP(N87,$B$3:$G$508,6,0),0) -> 0 | Q87: =PRODUCT(O87,P87) -> 0
A88: 45554 | B88: Router Bit Force 5001 | C88: 621101840030 | D88: 45554 | E88: Router Bit Force 5001 | F88: PCS | G88: 25 | H88: AL BAHAR DN-15011 | I88: CARPENTER CON | J88: CARPENTER | M88: =IFERROR(VLOOKUP(N88,$B$3:$G$508,3,0),0) -> 0 | O88: =IFERROR(VLOOKUP(N88,$B$3:$G$508,6,0),0) -> 0 | Q88: =PRODUCT(O88,P88) -> 0
A89: 45546 | B89: Plain MDF Board - 9mm Malaysia - MD09 | C89: 401091620018 | D89: 45546 | E89: Plain MDF Board - 9mm Malaysia - MD09 | F89: SHT | G89: 30 | H89: GRAND STORE DN NO-107105 | I89: CARPENTER | J89: CARPENTER | M89: =IFERROR(VLOOKUP(N89,$B$3:$G$508,3,0),0) -> 0 | O89: =IFERROR(VLOOKUP(N89,$B$3:$G$508,6,0),0) -> 0 | Q89: =PRODUCT(O89,P89) -> 0
A90: 45519 | B90: Jig Saw Blade B24/T1186 (5Pcs/Pkt) | C90: 401101840033 | D90: 45519 | E90: Jig Saw Blade B24/T1186 (5Pcs/Pkt) | F90: PKT | G90: 18 | H90: AL -ABDULLA DN NO - 21437 | I90: CARPENTER CON | J90: CARPENTER | M90: =IFERROR(VLOOKUP(N90,$B$3:$G$508,3,0),0) -> 0 | O90: =IFERROR(VLOOKUP(N90,$B$3:$G$508,6,0),0) -> 0 | Q90: =PRODUCT(O90,P90) -> 0
A91: 45518 | B91: Twist Drill Bits 9mm | C91: 401101840052 | D91: 45518 | E91: Twist Drill Bits 9mm | F91: Pcs | G91: 18 | H91: AL BAHAR DN NO - 14785 | I91: CARPENTER CON | J91: CARPENTER | M91: =IFERROR(VLOOKUP(N91,$B$3:$G$508,3,0),0) -> 0 | O91: =IFERROR(VLOOKUP(N91,$B$3:$G$508,6,0),0) -> 0 | Q91: =PRODUCT(O91,P91) -> 0
A92: 45517 | B92: Makita Hss Dril Bit 9mm | C92: 401101910009 | D92: 45517 | E92: Makita Hss Dril Bit 9mm | F92: PCS | G92: 13 | H92: AL ABDULLA DN NO - 21432 | I92: CARPENTER CON | J92: CARPENTER | M92: TOTAL PRICE | Q92: =SUM(Q82:Q91) -> 0
A93: 45512 | B93: Wood Nail ¾ Headless - Lost Head Nail | C93: 401101840302 | D93: 45512 | E93: Wood Nail ¾ Headless - Lost Head Nail | F93: Pkt | G93: 4.25 | H93: AL ABDULLA DN NO- 21416 | I93: CARPENTER CON | J93: CARPENTER
A94: 45512 | B94: SK Premium Screw Bit PH2 50mm | C94: 621101840004 | D94: 45512 | E94: SK Premium Screw Bit PH2 50mm | F94: PCS | G94: 5 | H94: AL BAHAR DN NO- 14769 | I94: CARPENTER CON | J94: CARPENTER | M94: PRINT
A95: 45502 | B95: Hss Drill Bit 13mm | C95: 401101840323 | D95: 45502 | E95: Hss Drill Bit 13mm | F95: Pcs | G95: 24 | H95: AL BAHAR DN - 14636 | I95: CARPENTER CON | J95: CARPENTER | M95: DATE OF DELIVERY | N95: ITEM DESCRIPTION | O95: UNIT PRICE | P95: QTY | Q95: TOTAL PRICE
A96: 45497 | B96: Jumbo MDF 6x12x12mm | C96: 541101840002 | D96: 45497 | E96: Jumbo MDF 6x12x12mm | F96: SHT | G96: 115 | H96: BBMC DN NO - 24200740 | I96: CARPENTER | J96: CARPENTER | M96: =IFERROR(VLOOKUP(N96,$B$3:$G$508,3,0),0) -> 0 | O96: =IFERROR(VLOOKUP(N96,$B$3:$G$508,6,0),0) -> 0 | Q96: =PRODUCT(O96,P96) -> 0
A97: 45484 | B97: Makita Hss Dril Bit 8mm | C97: 401101910008 | D97: 45484 | E97: Makita Hss Dril Bit 8mm | F97: PCS | G97: 8 | H97: AL- ABDULLA TRD&CO. DN NO- 21739 | I97: CARPENTER CON | J97: CARPENTER | M97: =IFERROR(VLOOKUP(N97,$B$3:$G$508,3,0),0) -> 0 | O97: =IFERROR(VLOOKUP(N97,$B$3:$G$508,6,0),0) -> 0 | Q97: =PRODUCT(O97,P97) -> 0
A98: 45481 | B98: 2x4x4Mtr White Wood - Austria | C98: 401101620008 | D98: 45481 | E98: 2x4x4Mtr White Wood - Austria | F98: PCS | G98: 21 | H98: GRAND STORE DN-104085 | I98: CARPENTER | J98: CARPENTER | M98: =IFERROR(VLOOKUP(N98,$B$3:$G$508,3,0),0) -> 0 | O98: =IFERROR(VLOOKUP(N98,$B$3:$G$508,6,0),0) -> 0 | Q98: =PRODUCT(O98,P98) -> 0
A99: 45481 | B99: Commercial Plywood 4x8x6mm - Indonesia KP07 | C99: 401091620008 | D99: 45481 | E99: Commercial Plywood 4x8x6mm - Indonesia KP07 | F99: SHT | G99: 26 | H99: GRAND STORE DN-104114 | I99: CARPENTER | J99: CARPENTER | M99: =IFERROR(VLOOKUP(N99,$B$3:$G$508,3,0),0) -> 0 | O99: =IFERROR(VLOOKUP(N99,$B$3:$G$508,6,0),0) -> 0 | Q99: =PRODUCT(O99,P99) -> 0
A100: 45475 | B100: Fibre Board (MDF) 4x8x 3mm - MD03 | C100: 401101620001 | D100: 45475 | E100: Fibre Board (MDF) 4x8x 3mm - MD03 | F100: SHT | G100: 10.5 | H100: GRAND STORE DN-103826,103827,103832,103828 | I100: CARPENTER | J100: CARPENTER | M100: =IFERROR(VLOOKUP(N100,$B$3:$G$508,3,0),0) -> 0 | O100: =IFERROR(VLOOKUP(N100,$B$3:$G$508,6,0),0) -> 0 | Q100: =PRODUCT(O100,P100) -> 0
...

Sheet WORK  
A1: STEEL FABRICATION MATERIALS
A2: DATE | B2: ITEM DESCRIPTION | C2: UOM | D2: APPROXIMATE COST | E2: SUPPLIER
A3: 45636 | B3: STEEL TUBE 30X30X1.5MM | C3: Pcs | D3: 22.5 | E3: QATAR STEEL , AL ITTEFAQ
A4: 45634 | B4: Rec.Angle Tube 40x20x1.5mm | C4: PCS | D4: 22 | E4: QATAR STEEL , AL ITTEFAQ
A5: 45634 | B5: STEEL TUBE 40X40X1.5MM | C5: Pcs | D5: 29.5 | E5: QATAR STEEL , AL ITTEFAQ
A6: 45631 | B6: STEEL PIPE 3cmx1.5mm | C6: Pcs | D6: 32 | E6: QATAR STEEL , AL ITTEFAQ
A7: 45630 | B7: G.I Pipe 1"- ½ X3X6m | C7: PCS | D7: 66.75 | E7: QATAR STEEL , AL ITTEFAQ
A8: 45630 | B8: STEEL TUBE 16X16X1.5MM | C8: Pcs | D8: 12.25 | E8: QATAR STEEL , AL ITTEFAQ
A9: 45623 | B9: Round Bar 8mm | C9: Pcs | D9: 7.5 | E9: QATAR STEEL , AL ITTEFAQ
A10: 45620 | B10: STEEL TUBE 25X25X1.5MM | C10: Pcs | D10: 20 | E10: QATAR STEEL , AL ITTEFAQ
A11: 45612 | B11: STEEL TUBE 19X19X1.5MM | C11: PCS | D11: 14.9 | E11: QATAR STEEL , AL ITTEFAQ
A12: 45571 | B12: Flat Bar 40x4x6mtr | C12: PCS | D12: 22.5 | E12: QATAR STEEL , AL ITTEFAQ
A13: 45556 | B13: G.I Pipe 4"X2mmX6m | C13: PCS | D13: 106 | E13: QATAR STEEL , AL ITTEFAQ
A14: 45551 | B14: Round Bar 12mmX6mtr | C14: PCS | D14: 17.5 | E14: QATAR STEEL , AL ITTEFAQ
... A34: 45307 | B34: Makita Cutting Disc 4.5" (115x1.2mm) | C34: PCS | D34: 3 | E34: AL ABDULLA TRDG , AL BAHAR
A35: CARPENTER MATERIALS
B36: ITEM DESCRIPTION | C36: UOM | D36: APPROXIMATE COST | E36: SUPPLIER
A37: 45635 | B37: Commercial Plywood 4x8x9mm - Malaysia - KP09 | C37: SHT | D37: 45 | E37: BBMC , GRAND STORE
A38: 45633 | B38: Fibre Board(MDF) - 4x8x12MM - MD12 | C38: SHT | D38: 39 | E38: BBMC , GRAND STORE
A39: 45633 | B39: Fibre Board(MDF) - 4x8x6MM - MD06 | C39: SHT | D39: 20 | E39: BBMC , GRAND STORE
A40: 45627 | B40: Austrian White Wood -morabaa- 2x2x13 - AW22 | C40: Pcs | D40: 11 | E40: BBMC , GRAND STORE
A41: 45602 | B41: Fibre Board (MDF) 16MM | C41: SHT | D41: 46 | E41: BBMC , GRAND STORE
A42: 45601 | B42: Fibre Board (MDF) 4x8x 9mm - MD09 | C42: SHT | D42: 28 | E42: BBMC , GRAND STORE
A43: 45594 | B43: Polycarbonate Sheet clear Obscure 2.5mm | C43: SHT | D43: 350 | E43: SABIN PLASTIC , WORLD OF MATERIALS
A44: 45546 | B44: Plain MDF Board - 9mm Malaysia - MD09 | C44: SHT | D44: 30 | E44: BBMC , GRAND STORE
A45: 45497 | B45: Jumbo MDF 6x12x12mm | C45: SHT | D45: 115 | E45: BBMC , GRAND STORE
A46: 45481 | B46: 2x4x4Mtr White Wood - Austria | C46: PCS | D46: 21 | E46: BBMC , GRAND STORE
A47: 45481 | B47: Commercial Plywood 4x8x6mm - Indonesia KP07 | C47: SHT | D47: 26 | E47: BBMC , GRAND STORE
A48: 45475 | B48: Fibre Board (MDF) 4x8x 3mm - MD03 | C48: SHT | D48: 10.5 | E48: BBMC , GRAND STORE
... A126: 45300 | B126: Wood Nails 1" | C126: PKT | D126: 2.19 | E126: AL ABDULLA , AL BAHAR
A127: FOAM AND ACRYLIC AND FOREX WORK MATERIALS
B128: ITEM DESCRIPTION | C128: UOM | D128: APPROXIMATE COST | E128: SUPPLIER
A129: 45619 | B129: Forex Sheet White 2mm | C129: Sht | D129: 19 | E129: SABIN PLASTIC , WORLD OF MATERIALS
A130: 45619 | B130: Forex Sheet White 1mm | C130: SHT | D130: 15 | E130: SABIN PLASTIC , WORLD OF MATERIALS
A131: 45615 | B131: Acrylic Silver Mirror 122x244 - 2mm | C131: SHT | D131: 135 | E131: SABIN PLASTIC , WORLD OF MATERIALS
A132: 45594 | B132: Acrylic 122 X 240 X 2.0mm Black | C132: SHT | D132: 110 | E132: SABIN PLASTIC , WORLD OF MATERIALS
A133: 45584 | B133: Forex Sheet White 4mm | C133: SHT | D133: 34 | E133: SABIN PLASTIC , WORLD OF MATERIALS
A134: 45584 | B134: Forex sheet white 3mm | C134: SHT | D134: 26 | E134: SABIN PLASTIC , WORLD OF MATERIALS
A135: 45549 | B135: Eps Sheet 244x122x3cm D-16-18K.g | C135: SHT | D135: 21.88 | E135: NAFA, NATIONAL POLYSTYRENE PRODUCTS FACTORY QATAR
A136: 45533 | B136: Eps Sheet 244x122x5cm | C136: PCS | D136: 31.5 | E136: NAFA, NATIONAL POLYSTYRENE PRODUCTS FACTORY QATAR
A137: 45444 | B137: Acrylic Clear Sheet 2.8mm | C137: PCS | D137: 125 | E137: SABIN PLASTIC , WORLD OF MATERIALS
A138: 45420 | B138: Eps Sheet 200x100x5cm | C138: SHT | D138: 21 | E138: NAFA, NATIONAL POLYSTYRENE PRODUCTS FACTORY QATAR
A139: 45420 | B139: Eps Sheet 200x100x10cm | C139: SHT | D139: 42 | E139: NAFA, NATIONAL POLYSTYRENE PRODUCTS FACTORY QATAR
A140: 45409 | B140: Eps Sheet 244x120x5cm 14-16 | C140: SHT | D140: 35 | E140: NAFA, NATIONAL POLYSTYRENE PRODUCTS FACTORY QATAR
... A147: 45300 | B147: EPS FOAM BLOCK 500X120X100CM D16-1 | C147: BLOCK | D147: 1100 | E147: NATIONAL POLYSTYRENE PRODUCTS FACTORY QATAR
A148: GENERAL WORK MATERIALS
B149: ITEM DESCRIPTION | C149: UOM | D149: APPROXIMATE COST | E149: SUPPLIER
A150: 45638 | B150: Olfa Blade - AB10 | C150: PKT | D150: 12 | E150: AL ABDULLA TRDG , AL BAHAR
A151: 45633 | B151: Cable Tie 500X 7.6mm | C151: PKT | D151: 24 | E151: AL ABDULLA TRDG , AL BAHAR , THE D COMPANY
A152: 45631 | B152: Super Glue | C152: PCS | D152: 1.5 | E152: AL ABDULLA TRDG , AL BAHAR
A153: 45631 | B153: Clear Tape 2" Conic | C153: PCS | D153: 2.9 | E153: AL ABDULLA TRDG , AL BAHAR
A154: 45626 | B154: Kitchen Cloth 10Pcs | C154: PCS | D154: 1.8 | E154: HEAD OFFICE
A155: 45623 | B155: Polyfix Foam Spary 750ML | C155: PCS | D155: 15 | E155: AL ABDULLA TRDG , AL BAHAR
A156: 45619 | B156: Akfix 705 Bonds Glue 100+400Ml | C156: PCS | D156: 25 | E156: AL ABDULLA TRDG , AL BAHAR
A157: 45619 | B157: Bubble Roll 1.5MX75 Yards | C157: Rol | D157: 70 | E157: PETROFOAM
A158: 45619 | B158: GARBAGE BAGS BLACK 80 X 110 | C158: BDL | D158: 110 | E158: ORIENT PLASTIC
A159: 45615 | B159: Hand Glows - Doted | C159: PAR | D159: 1.5 | E159: AL ABDULLA TRDG , AL BAHAR
A160: 45613 | B160: Cable Tie 550X 7.6mm | C160: Pkt | D160: 29 | E160: AL ABDULLA TRDG , AL BAHAR
A161: 45605 | B161: Clear Tape 2" Asmaco - UAE | C161: PCS | D161: 2 | E161: AL ABDULLA TRDG , AL BAHAR
... A179: 45332 | B179: Foam Spray - 750ml | C179: Pcs | D179: 20 | E179: AL ABDULLA TRDG , AL BAHAR , THE D COMPANY
A180: PAINTER MATERIALS
B181: ITEM DESCRIPTION | C181: UOM | D181: APPROXIMATE COST | E181: SUPPLIER
A182: 45638 | B182: Stucco Putty - Jotun - 20L | C182: DRM | D182: 64 | E182: AL ABDULLA TRDG , AL BAHAR
A183: 45636 | B183: Jotun Fenomastic Matt White Water Base - Emulsion | C183: DRM | D183: 275 | E183: AL ABDULLA TRDG , AL BAHAR
A184: 45624 | B184: EBM N C Lacquer Thinner TH 240 3.0 LTR | C184: GAL | D184: 27 | E184: AL ABDULLA TRDG , AL BAHAR
A185: 45638 | B185: Abrasive paper (SAND PAPER) - 320 Korea | C185: Pcs | D185: 0.9 | E185: AL ABDULLA TRDG , AL BAHAR
A186: 45638 | B186: Mini paint roller 4" Refiller | C186: PCS | D186: 1.5 | E186: AL ABDULLA TRDG , AL BAHAR
A187: 45638 | B187: Hand brush 2" | C187: PCS | D187: 3.5 | E187: AL ABDULLA TRDG , AL BAHAR
A188: 45638 | B188: Hand Brush Petta - 1" - Oryx | C188: PCS | D188: 3 | E188: AL ABDULLA TRDG , AL BAHAR
A189: 45636 | B189: Easy Colour Blue 717 - 250Ml | C189: BTL | D189: 42 | E189: AL ABDULLA TRDG , AL BAHAR
A190: 45636 | B190: Abrasive paper (SAND PAPER) - 180 Korea | C190: SHT | D190: 0.9 | E190: AL ABDULLA TRDG , AL BAHAR
A191: 45636 | B191: Yellow Oxide APS3682 | C191: PCS | D191: 105 | E191: AL ABDULLA TRDG , AL BAHAR
A192: 45636 | B192: Jotashield ABGC 8080 - 18L | C192: DRM | D192: 380 | E192: AL ABDULLA TRDG , AL BAHAR
A193: 45636 | B193: Easy Colour 719 - 100 ML | C193: NOS | D193: 19 | E193: AL ABDULLA TRDG , AL BAHAR
... A251: 45327 | B251: Masking Tape 48mm - 2" (2x30 Yard) | C251: PCS | D251: 1.17 | E251: AL ABDULLA TRDG , AL BAHAR , BOSCO
B252: Masking Tape 24mm - 1"(1x30 Yard) | C252: RL | D252: 0.9 | E252: AL ABDULLA TRDG , AL BAHAR , BOSCO
B253: Masking Tape - 2" Oxya | C253: RL | D253: 2.52 | E253: AL ABDULLA TRDG , AL BAHAR , BOSCO
A254: 45327 | B254: Masking Tape 24mm - 1"(1x30 Yard) | C254: PCS | D254: 0.92 | E254: AL ABDULLA TRDG , AL BAHAR , BOSCO
A255: TAILOR MATERIALS
B256: ITEM DESCRIPTION | C256: UOM | D256: APPROXIMATE COST | E256: SUPPLIER
B257: Stapler Gun Rapid R23 | C257: Pcs | D257: 105 | E257: AL BAHAR , AL ABDULLA TRDG
A258: 45636 | B258: Stapler pin 13/8 for Rapid gun | C258: Pcs | D258: 8 | E258: AL BAHAR , AL ABDULLA TRDG
A259: 45292 | B259: FABRIC (IN GENERAL) | C259: MTR | D259: 15 | E259: AL SHAHAB
A260: 45292 | B260: SHIFFON (IN GENERAL) | C260: MTR | D260: 4.5 | E260: AL SHAHAB
A261: 45292 | B261: MOKMOL (IN GENERAL) | C261: MTR | D261: 15 | E261: AL SHAHAB
A262: PARKE
B263: ITEM DESCRIPTION | C263: UOM | D263: APPROXIMATE COST | E263: SUPPLIER
A264: 45370 | B264: Vinyl Sheet (Parke) - 139L (W4MTR X L30MTR) (AS PER MTR) | C264: MTR | D264: 85 | E264: ALWAN FURNITURE
A265: 45370 | B265: Parke Montreal 194 L (W4MTR X L30MTR)(AS PER MTR) | C265: MTR | D265: 85 | E265: ALWAN FURNITURE
A266: 45405 | B266: Parke Pauda 532 (W4MTR X L30MTR)(AS PER MTR) | C266: MTR | D266: 77.75 | E266: ALWAN FURNITURE
A267: 45405 | B267: Parke 901 D (W4MTR X L30MTR)(AS PER MTR) | C267: MTR | D267: 77.75 | E267: ALWAN FURNITURE
A268: 45524 | B268: Parke Atlantic Midas 036 L (W4MTR X L30MTR)(AS PER MTR) | C268: MTR | D268: 81.9 | E268: ALWAN FURNITURE

Sheet MAIN WITH ITEM CODE 0
A1: DATE | B1: ITEM CODE | C1: DATE | D1: ITEM DESCRIPTION | E1: UOM | F1: DELIVERY | G1: COST | H1: D/N NO AND R/V NO
A2: 45638 | B2: 401101840025 | C2: 45638 | D2: Screw 3" x8 black - (250/300 Pkt) | E2: PKT | F2: 200 | G2: 17.5 | H2: AL ABDULLA TRDG DN-22834
A3: 45638 | B3: 091101840002 | C3: 45638 | D3: Grinding Disk 4.5" (CUTTING DISC 4.5") | E3: PCS | F3: 100 | G3: 3.5 | H3: AL ABDULLA TRDG DN-22834
A4: 45638 | B4: 401101840296 | C4: 45638 | D4: Abrasive paper (SAND PAPER) - 320 Korea | E4: Pcs | F4: 100 | G4: 0.9 | H4: AL ABDULLA TRDG DN-22834
A5: 45638 | B5: 401101840019 | C5: 45638 | D5: Mini paint roller 4" Refiller | E5: PCS | F5: 170 | G5: 1.5 | H5: AL ABDULLA TRDG DN-22834
A6: 45638 | B6: 401101840006 | C6: 45638 | D6: Hand brush 2" /HAVING MORTHAN 2 ITEM NO | E6: PCS | F6: 12 | G6: 3.5 | H6: AL ABDULLA TRDG DN-22834
A7: 45638 | B7: 401101840131 | C7: 45638 | D7: Hand Brush Petta - 1" - Oryx /HAVING MORTHAN 2 ITEM NO | E7: PCS | F7: 12 | G7: 3 | H7: AL ABDULLA TRDG DN-22834
A8: 45638 | B8: 581101840004 | C8: 45638 | D8: Brad Nail Billionaire - F 20 (5000/Pkt) | E8: PKT | F8: 20 | G8: 12 | H8: AL ABDULLA TRDG DN-22834
A9: 45638 | B9: 591101840019 | C9: 45638 | D9: Stucco Putty - Jotun - 20L | E9: DRM | F9: 10 | G9: 64 | H9: AL ABDULLA TRDG DN-22834
A10: 45638 | B10: 401101840214 | C10: 45638 | D10: Olfa Blade - AB10 | E10: PKT | F10: 30 | G10: 12 | H10: AL ABDULLA TRDG DN-22834
A11: 45638 | B11: 591101840019 | C11: 45638 | D11: Stucco Putty - Jotun - 20L | E11: DRM | F11: 10 | G11: 64 | H11: AL BAHAR DN-15307
A12: 45638 | B12: 401101840025 | C12: 45638 | D12: Screw 3" x8 black - (250/300 Pkt) | E12: PKT | F12: 200 | G12: 17.5 | H12: AL BAHAR DN-15307
A13: 45638 | B13: 091101840002 | C13: 45638 | D13: Grinding Disk 4.5" (CUTTING DISC 4.5") | E13: PCS | F13: 100 | G13: 3.5 | H13: AL BAHAR DN-15307
... A1228: 45294 | B1228: 401101620001 | C1228: 45294 | D1228: Fibre Board (MDF) 4x8x 3mm - MD03 /HAVING MORTHAN 2 ITEM NO | E1228: SHT | F1228: 500 | G1228: 10.5 | H1228: BBMC DN-24200011

Sheet MAIN WITH ITEM CODE 1
A1: DATE | B1: ITEM CODE | C1: ITEM DESCRIPTION | D1: UOM | E1: COST | F1: D/N NO | G1: CATEGORY
A2: 45638 | B2: 401101840025 | C2: Screw 3" x8 black - (250/300 Pkt) | D2: PKT | E2: 17.5 | F2: AL ABDULLA TRDG DN-22834 | G2: CARPENTER
A3: 45638 | B3: 091101840002 | C3: Grinding Disk 4.5" (CUTTING DISC 4.5") | D3: PCS | E3: 3.5 | F3: AL ABDULLA TRDG DN-22834 | G3: STEEL FABRICATION
A4: 45638 | B4: 401101840296 | C4: Abrasive paper (SAND PAPER) - 320 Korea | D4: Pcs | E4: 0.9 | F4: AL ABDULLA TRDG DN-22834 | G4: PAINTER
A5: 45638 | B5: 401101840019 | C5: Mini paint roller 4" Refiller | D5: PCS | E5: 1.5 | F5: AL ABDULLA TRDG DN-22834 | G5: PAINTER
A6: 45638 | B6: 401101840006 | C6: Hand brush 2" | D6: PCS | E6: 3.5 | F6: AL ABDULLA TRDG DN-22834 | G6: PAINTER
A7: 45638 | B7: 401101840131 | C7: Hand Brush Petta - 1" - Oryx | D7: PCS | E7: 3 | F7: AL ABDULLA TRDG DN-22834 | G7: PAINTER
A8: 45638 | B8: 581101840004 | C8: Brad Nail Billionaire - F 20 (5000/Pkt) | D8: PKT | E8: 12 | F8: AL ABDULLA TRDG DN-22834 | G8: CARPENTER
A9: 45638 | B9: 591101840019 | C9: Stucco Putty - Jotun - 20L | D9: DRM | E9: 64 | F9: AL ABDULLA TRDG DN-22834 | G9: PAINTER
A10: 45638 | B10: 401101840214 | C10: Olfa Blade - AB10 | D10: PKT | E10: 12 | F10: AL ABDULLA TRDG DN-22834 | G10: GENERAL WORK
A11: 45636 | B11: 401101840248 | C11: Jotun Fenomastic Matt White Water Base - Emulsion | D11: DRM | E11: 275 | F11: AL ABDUULLA DN NO- 22831 | G11: PAINTER
A12: 45636 | B12: 401101840266 | C12: Easy Colour Blue 717 - 250Ml | D12: BTL | E12: 42 | F12: AL ABDUULLA DN NO- 22831 | G12: PAINTER
A13: 45636 | B13: 401101840092 | C13: Abrasive paper (SAND PAPER) - 180 Korea | D13: SHT | E13: 0.9 | F13: AL ABDUULLA DN NO- 22831 | G13: PAINTER
... A245: 45300 | B245: 127 | C245: EPS FOAM BLOCK 500X120X100CM D16-1 | D245: BLOCK | E245: 1100 | F245: NPPF | G245: FOAM AND DESIGN WORK

Sheet MAIN WITHOUT ITEM CODE 0
A1: DATE | B1: ITEM CODE | C1: DATE | D1: ITEM DESCRIPTION | E1: UOM | F1: DELIVERY | G1: COST | H1: D/N NO AND R/V NO
A2: 45638 | B2: 1193 | C2: 45638 | D2: Measuring Tape - 5 mtr | E2: Pcs | F2: 6 | G2: 0 | H2: AL ABDULLA TRDG DN-22834
A3: 45638 | B3: 1190 | C3: 45638 | D3: Knipex Cutter - Germany | E3: Pcs | F3: 10 | G3: 0 | H3: AL ABDULLA TRDG DN-22834
A4: 45638 | B4: 1354 | C4: 45638 | D4: NYLONE ROPE 10MM - 100MTR | E4: RL | F4: 5 | G4: 0 | H4: AL BAHAR DN-15307
A5: 45638 | B5: 1193 | C5: 45638 | D5: Measuring Tape - 5 mtr | E5: Pcs | F5: 6 | G5: 0 | H5: AL BAHAR DN-15307
A6: 45636 | B6: 1122 | C6: 45636 | D6: Safety Glass Black | E6: Pcs | F6: 12 | G6: 0 | H6: AL ABDUULLA DN NO- 22831
A7: 45636 | B7: 1122 | C7: 45636 | D7: Safety Glass Black | E7: Pcs | F7: 12 | G7: 0 | H7: AL BAHAR DN NO-16043
A8: 45631 | B8: 1455 | C8: 45631 | D8: ROBUSTLINE DOOR HINGES 4" | E8: PCS | F8: 10 | G8: 0 | H8: AL ABDULLA TRDG DN-22817
A9: 45631 | B9: 1455 | C9: 45631 | D9: ROBUSTLINE DOOR HINGES 4" | E9: PCS | F9: 10 | G9: 0 | H9: AL BAHAR DN-16027
A10: 45631 | B10: 1190 | C10: 45631 | D10: Knipex Cutter - Germany | E10: Pcs | F10: 10 | G10: 0 | H10: AL BAHAR DN-16027
A11: 45629 | B11: 1164 | C11: 45629 | D11: Water filter | E11: Pcs | F11: 20 | G11: 0 | H11: AL BAHAR DN NO- 16023
A12: 45629 | B12: 1372 | C12: 45629 | D12: SCRAPER SET SMALL | E12: SET | F12: 15 | G12: 0 | H12: AL BAHAR DN NO- 16023
A13: 45628 | B13: 1164 | C13: 45628 | D13: Water filter | E13: Pcs | F13: 20 | G13: 0 | H13: AL ABDULLA TRDG DN-22811
... A170: 45302 | B170: 1164 | C170: 45302 | D170: Water filter | E170: Pcs | F170: 50 | G170: 0 | H170: RED PHOENIX DN-4477

Sheet MAIN WITHOUT ITEM CODE 1
A1: DATE | B1: ITEM CODE | C1: ITEM DESCRIPTION | D1: UOM | E1: D/N NO | F1: COST
A2: 45638 | B2: 1193 | C2: =IFERROR(VLOOKUP(B2,'MAIN WITHOUT ITEM CODE 0'!$B$2:$H$170,3,0),0) -> Measuring Tape - 5 mtr | D2: =IFERROR(VLOOKUP(B2,'MAIN WITHOUT ITEM CODE 0'!$B$2:$H$170,4,0),0) -> Pcs | E2: =IFERROR(VLOOKUP(B2,'MAIN WITHOUT ITEM CODE 0'!$B$2:$H$170,7,0),0) -> AL ABDULLA TRDG DN-22834
A3: 45638 | B3: 1190 | C3: =IFERROR(VLOOKUP(B3,'MAIN WITHOUT ITEM CODE 0'!$B$2:$H$170,3,0),0) -> Knipex Cutter - Germany | D3: =IFERROR(VLOOKUP(B3,'MAIN WITHOUT ITEM CODE 0'!$B$2:$H$170,4,0),0) -> Pcs | E3: =IFERROR(VLOOKUP(B3,'MAIN WITHOUT ITEM CODE 0'!$B$2:$H$170,7,0),0) -> AL ABDULLA TRDG DN-22834
A4: 45638 | B4: 1354 | C4: =IFERROR(VLOOKUP(B4,'MAIN WITHOUT ITEM CODE 0'!$B$2:$H$170,3,0),0) -> NYLONE ROPE 10MM - 100MTR | D4: =IFERROR(VLOOKUP(B4,'MAIN WITHOUT ITEM CODE 0'!$B$2:$H$170,4,0),0) -> RL | E4: =IFERROR(VLOOKUP(B4,'MAIN WITHOUT ITEM CODE 0'!$B$2:$H$170,7,0),0) -> AL BAHAR DN-15307
A5: 45636 | B5: 1122 | C5: =IFERROR(VLOOKUP(B5,'MAIN WITHOUT ITEM CODE 0'!$B$2:$H$170,3,0),0) -> Safety Glass Black | D5: =IFERROR(VLOOKUP(B5,'MAIN WITHOUT ITEM CODE 0'!$B$2:$H$170,4,0),0) -> Pcs | E5: =IFERROR(VLOOKUP(B5,'MAIN WITHOUT ITEM CODE 0'!$B$2:$H$170,7,0),0) -> AL ABDUULLA DN NO- 22831
A6: 45631 | B6: 1455 | C6: =IFERROR(VLOOKUP(B6,'MAIN WITHOUT ITEM CODE 0'!$B$2:$H$170,3,0),0) -> ROBUSTLINE DOOR HINGES 4" | D6: =IFERROR(VLOOKUP(B6,'MAIN WITHOUT ITEM CODE 0'!$B$2:$H$170,4,0),0) -> PCS | E6: =IFERROR(VLOOKUP(B6,'MAIN WITHOUT ITEM CODE 0'!$B$2:$H$170,7,0),0) -> AL ABDULLA TRDG DN-22817
A7: 45629 | B7: 1164 | C7: =IFERROR(VLOOKUP(B7,'MAIN WITHOUT ITEM CODE 0'!$B$2:$H$170,3,0),0) -> Water filter | D7: =IFERROR(VLOOKUP(B7,'MAIN WITHOUT ITEM CODE 0'!$B$2:$H$170,4,0),0) -> Pcs | E7: =IFERROR(VLOOKUP(B7,'MAIN WITHOUT ITEM CODE 0'!$B$2:$H$170,7,0),0) -> AL BAHAR DN NO- 16023
A8: 45629 | B8: 1372 | C8: =IFERROR(VLOOKUP(B8,'MAIN WITHOUT ITEM CODE 0'!$B$2:$H$170,3,0),0) -> SCRAPER SET SMALL | D8: =IFERROR(VLOOKUP(B8,'MAIN WITHOUT ITEM CODE 0'!$B$2:$H$170,4,0),0) -> SET | E8: =IFERROR(VLOOKUP(B8,'MAIN WITHOUT ITEM CODE 0'!$B$2:$H$170,7,0),0) -> AL BAHAR DN NO- 16023
A9: 45624 | B9: 1336 | C9: =IFERROR(VLOOKUP(B9,'MAIN WITHOUT ITEM CODE 0'!$B$2:$H$170,3,0),0) -> TARPAULIN SHEET 40X40 | D9: =IFERROR(VLOOKUP(B9,'MAIN WITHOUT ITEM CODE 0'!$B$2:$H$170,4,0),0) -> SHT | E9: =IFERROR(VLOOKUP(B9,'MAIN WITHOUT ITEM CODE 0'!$B$2:$H$170,7,0),0) -> AL BAHAR DN-16016
A10: 45619 | B10: 1166 | C10: =IFERROR(VLOOKUP(B10,'MAIN WITHOUT ITEM CODE 0'!$B$2:$H$170,3,0),0) -> Welding Electrode E6013 | D10: =IFERROR(VLOOKUP(B10,'MAIN WITHOUT ITEM CODE 0'!$B$2:$H$170,4,0),0) -> Pkt | E10: =IFERROR(VLOOKUP(B10,'MAIN WITHOUT ITEM CODE 0'!$B$2:$H$170,7,0),0) -> AL ABDULLA TRDG DN-22140 | F10: 14
A11: 45619 | B11: 1149 | C11: =IFERROR(VLOOKUP(B11,'MAIN WITHOUT ITEM CODE 0'!$B$2:$H$170,3,0),0) -> Steel Angle 2 Hole 30x30x15mm | D11: =IFERROR(VLOOKUP(B11,'MAIN WITHOUT ITEM CODE 0'!$B$2:$H$170,4,0),0) -> Pcs | E11: =IFERROR(VLOOKUP(B11,'MAIN WITHOUT ITEM CODE 0'!$B$2:$H$170,7,0),0) -> AL ABDULLA TRDG DN-22140
A12: 45614 | B12: 1024 | C12: =IFERROR(VLOOKUP(B12,'MAIN WITHOUT ITEM CODE 0'!$B$2:$H$170,3,0),0) -> Binding wire gauge-16 | D12: =IFERROR(VLOOKUP(B12,'MAIN WITHOUT ITEM CODE 0'!$B$2:$H$170,4,0),0) -> Roll | E12: =IFERROR(VLOOKUP(B12,'MAIN WITHOUT ITEM CODE 0'!$B$2:$H$170,7,0),0) -> AL BAHAR DN-15246
A13: 45608 | B13: 1465 | C13: =IFERROR(VLOOKUP(B13,'MAIN WITHOUT ITEM CODE 0'!$B$2:$H$170,3,0),0) -> PVC COATED WIRE ROPE 2MM | D13: =IFERROR(VLOOKUP(B13,'MAIN WITHOUT ITEM CODE 0'!$B$2:$H$170,4,0),0) -> PCS | E13: =IFERROR(VLOOKUP(B13,'MAIN WITHOUT ITEM CODE 0'!$B$2:$H$170,7,0),0) -> AL BAHAR DN NO- 15237
A14: 45606 | B14: 1175 | C14: =IFERROR(VLOOKUP(B14,'MAIN WITHOUT ITEM CODE 0'!$B$2:$H$170,3,0),0) -> Floor Cleaning Mope | D14: =IFERROR(VLOOKUP(B14,'MAIN WITHOUT ITEM CODE 0'!$B$2:$H$170,4,0),0) -> Pcs | E14: =IFERROR(VLOOKUP(B14,'MAIN WITHOUT ITEM CODE 0'!$B$2:$H$170,7,0),0) -> AL ABDULLA TRDG DN-22105
A15: 45605 | B15: 1059 | C15: =IFERROR(VLOOKUP(B15,'MAIN WITHOUT ITEM CODE 0'!$B$2:$H$170,3,0),0) -> Ear plug | D15: =IFERROR(VLOOKUP(B15,'MAIN WITHOUT ITEM CODE 0'!$B$2:$H$170,4,0),0) -> box | E15: =IFERROR(VLOOKUP(B15,'MAIN WITHOUT ITEM CODE 0'!$B$2:$H$170,7,0),0) -> AL ABDULLA DN NO - 22103
A16: 45605 | B16: 1082 | C16: =IFERROR(VLOOKUP(B16,'MAIN WITHOUT ITEM CODE 0'!$B$2:$H$170,3,0),0) -> Hammer (Small) - Patta | D16: =IFERROR(VLOOKUP(B16,'MAIN WITHOUT ITEM CODE 0'!$B$2:$H$170,4,0),0) -> Nos | E16: =IFERROR(VLOOKUP(B16,'MAIN WITHOUT ITEM CODE 0'!$B$2:$H$170,7,0),0) -> AL ABDULLA DN NO - 22103
A17: 45605 | B17: 1142 | C17: =IFERROR(VLOOKUP(B17,'MAIN WITHOUT ITEM CODE 0'!$B$2:$H$170,3,0),0) -> Socket 3/8 | D17: =IFERROR(VLOOKUP(B17,'MAIN WITHOUT ITEM CODE 0'!$B$2:$H$170,4,0),0) -> PCS | E17: =IFERROR(VLOOKUP(B17,'MAIN WITHOUT ITEM CODE 0'!$B$2:$H$170,7,0),0) -> AL BAHAR DN-15229
A18: 45602 | B18: 1396 | C18: =IFERROR(VLOOKUP(B18,'MAIN WITHOUT ITEM CODE 0'!$B$2:$H$170,3,0),0) -> WELDING CABLE 70MM | D18: =IFERROR(VLOOKUP(B18,'MAIN WITHOUT ITEM CODE 0'!$B$2:$H$170,4,0),0) -> MTR | E18: =IFERROR(VLOOKUP(B18,'MAIN WITHOUT ITEM CODE 0'!$B$2:$H$170,7,0),0) -> AL BAHAR DN NO- 15223
A19: 45602 | B19: 1192 | C19: =IFERROR(VLOOKUP(B19,'MAIN WITHOUT ITEM CODE 0'!$B$2:$H$170,3,0),0) -> Gypsum powder - 30 kg | D19: =IFERROR(VLOOKUP(B19,'MAIN WITHOUT ITEM CODE 0'!$B$2:$H$170,4,0),0) -> Nos | E19: =IFERROR(VLOOKUP(B19,'MAIN WITHOUT ITEM CODE 0'!$B$2:$H$170,7,0),0) -> AL BAHAR DN NO- 15223
A20: 45599 | B20: 1419 | C20: =IFERROR(VLOOKUP(B20,'MAIN WITHOUT ITEM CODE 0'!$B$2:$H$170,3,0),0) -> STEEL HAND BRUSH | D20: =IFERROR(VLOOKUP(B20,'MAIN WITHOUT ITEM CODE 0'!$B$2:$H$170,4,0),0) -> PCS | E20: =IFERROR(VLOOKUP(B20,'MAIN WITHOUT ITEM CODE 0'!$B$2:$H$170,7,0),0) -> AL ABDULLA DN NO-21986
A21: 45594 | B21: 1123 | C21: =IFERROR(VLOOKUP(B21,'MAIN WITHOUT ITEM CODE 0'!$B$2:$H$170,3,0),0) -> Safety Glass White | D21: =IFERROR(VLOOKUP(B21,'MAIN WITHOUT ITEM CODE 0'!$B$2:$H$170,4,0),0) -> Pcs | E21: =IFERROR(VLOOKUP(B21,'MAIN WITHOUT ITEM CODE 0'!$B$2:$H$170,7,0),0) -> AL ABDULLA TRDG DN-21971
A22: 45594 | B22: 1079 | C22: =IFERROR(VLOOKUP(B22,'MAIN WITHOUT ITEM CODE 0'!$B$2:$H$170,3,0),0) -> Gypsom Power | D22: =IFERROR(VLOOKUP(B22,'MAIN WITHOUT ITEM CODE 0'!$B$2:$H$170,4,0),0) -> Nos | E22: =IFERROR(VLOOKUP(B22,'MAIN WITHOUT ITEM CODE 0'!$B$2:$H$170,7,0),0) -> AL ABDULLA TRDG DN-21971
... A60: 45319 | B60: 1446 | C60: =IFERROR(VLOOKUP(B60,'MAIN WITHOUT ITEM CODE 0'!$B$2:$H$170,3,0),0) -> Fix Bolt 12mm | D60: =IFERROR(VLOOKUP(B60,'MAIN WITHOUT ITEM CODE 0'!$B$2:$H$170,4,0),0) -> PKT | E60: =IFERROR(VLOOKUP(B60,'MAIN WITHOUT ITEM CODE 0'!$B$2:$H$170,7,0),0) -> AL BAHAR DN-13606

Sheet COST 0
A1: CODE | B1: DESCRIPTION | C1: COST PRICE
A2: 010020020001 | B2: ALESSANDRO - ALBUM 228 -35X45 IVY SH 50-100+C | C2: 1479.32
A3: 010050060001 | B3: AYMAN SYR ALBUM - COL . Assort FLW -W/CASE-0 | C3: 299.96
A4: 010060070001 | B4: BIELLE BROWN FIORINO F7 (35X35) | C4: 287.89
A5: 010060070002 | B5: BIELLE P2 BLU F2 VERDE BLACK & RED | C5: 98
A6: 010060070003 | B6: C 100 ITALY LEATHER IVORY PAGES | C6: 811.59
A7: 010060070004 | B7: BIELLE ALBUM - IVORY FIORINO F1 - 35 X 35 | C7: 278.66
A8: 010060070005 | B8: BIELLE C2 - BLUE JEANS LEATHER IVORY PAGES | C8: 461.35
A9: 010060070006 | B9: BIELLE ALBUM P 2 VERDE | C9: 98
A10: 010060070007 | B10: BIELLE ALBUM P 2 BORO 5 | C10: 98
A11: 010060070008 | B11: BIELLE ALBUM F5 WALNUT FIORINO 35X35 40SH IVY | C11: 284.24
A12: 010060070009 | B12: BIELLE ALBUM - C127 GREEN OSTR IVY 35X35-LEA | C12: 1755.81
A13: 010060070010 | B13: BIELLE ALBUM - C128 WHITE COCCO IVY 35X35-LEA | C13: 1755.81
... A8305: 741101840001 | B8305: Wooden Legs For Chair And Table | C8305: 91.61

Sheet MAIN 0
A1: CODE | B1: DESCRIPTION | C1: COST PRICE
A2: 010020020001 | B2: ALESSANDRO - ALBUM 228 -35X45 IVY SH 50-100+C | C2: 1479.32
A3: 010050060001 | B3: AYMAN SYR ALBUM - COL . Assort FLW -W/CASE-0 | C3: 299.96
A4: 010060070001 | B4: BIELLE BROWN FIORINO F7 (35X35) | C4: 287.89
A5: 010060070002 | B5: BIELLE P2 BLU F2 VERDE BLACK & RED | C5: 98
A6: 010060070003 | B6: C 100 ITALY LEATHER IVORY PAGES | C6: 811.59
A7: 010060070004 | B7: BIELLE ALBUM - IVORY FIORINO F1 - 35 X 35 | C7: 278.66
A8: 010060070005 | B8: BIELLE C2 - BLUE JEANS LEATHER IVORY PAGES | C8: 461.35
A9: 010060070006 | B9: BIELLE ALBUM P 2 VERDE | C9: 98
A10: 010060070007 | B10: BIELLE ALBUM P 2 BORO 5 | C10: 98
A11: 010060070008 | B11: BIELLE ALBUM F5 WALNUT FIORINO 35X35 40SH IVY | C11: 284.24
A12: 010060070009 | B12: BIELLE ALBUM - C127 GREEN OSTR IVY 35X35-LEA | C12: 1755.81
A13: 010060070010 | B13: BIELLE ALBUM - C128 WHITE COCCO IVY 35X35-LEA | C13: 1755.81
... A6861: 741101840001 | B6861: Wooden Legs For Chair And Table | C6861: 91.61

Sheet STEEL MAIN
A1: DATE | B1: ITEM CODE | C1: ITEM DESCRIPTION | D1: UOM | E1: DELIVERY | F1: D/N NO AND R/V NO | G1: UNIT PRICE
A2: 45636 | B2: 401101840397 | C2: STEEL TUBE 30X30X1.5MM | D2: Pcs | E2: 50 | F2: QATAR STEEL DN NO- 74734 INV NO-120808 | G2: 22.5
A3: 45634 | B3: 401101840496 | C3: Rec.Angle Tube 40x20x1.5mm | D3: PCS | E3: 150 | F3: QATAR STEEL DN-74680 | G3: 22
A4: 45634 | B4: 401101840413 | C4: STEEL TUBE 40X40X1.5MM | D4: Pcs | E4: 50 | F4: QATAR STEEL DN-74680 | G4: 29.5
A5: 45630 | B5: 401101840442 | C5: STEEL TUBE 16X16X1.5MM | D5: Pcs | E5: 150 | F5: QATAR STEEL DN-24604 | G5: 12.25
A6: 45620 | B6: 401101840396 | C6: STEEL TUBE 25X25X1.5MM | D6: Pcs | E6: 200 | F6: QATAR STEEL DN-76442 | G6: 20
A7: 45612 | B7: 401101840397 | C7: STEEL TUBE 30X30X1.5MM | D7: Pcs | E7: 159 | F7: QATAR STEEL DN-76178 | G7: 22.5
A8: 45612 | B8: 401101840396 | C8: STEEL TUBE 25X25X1.5MM | D8: Pcs | E8: 520 | F8: QATAR STEEL DN-76178 | G8: 20
A9: 45612 | B9: 401101840493 | C9: STEEL TUBE 19X19X1.5MM | D9: PCS | E9: 100 | F9: QATAR STEEL DN-76178 | G9: 14.9
A10: 45610 | B10: 401101840396 | C10: STEEL TUBE 25X25X1.5MM | D10: Pcs | E10: 180 | F10: QATAR STEEL DN NO-76154 INV NO-119842 | G10: 20
A11: 45610 | B11: 401101840397 | C11: STEEL TUBE 30X30X1.5MM | D11: Pcs | E11: 121 | F11: QATAR STEEL DN NO-76154 INV NO-119842 | G11: 22.5
A12: 45607 | B12: 401101840413 | C12: STEEL TUBE 40X40X1.5MM | D12: Pcs | E12: 100 | F12: QATAR STEEL DN-76048 | G12: 29.5
A13: 45603 | B13: 401101840413 | C13: STEEL TUBE 40X40X1.5MM | D13: Pcs | E13: 250 | F13: QATAR STEEL DN-76925 | G13: 29.5
... A56: 45299 | B56: 401101840397 | C56: STEEL TUBE 30X30X1.5MM | D56: Pcs | E56: 70 | F56: QATAR STEEL DN-67560 | G56: 22.5
